kami_messenger/__init__.py
kami_messenger/botconversa/__init__.py
kami_messenger/botconversa/botconversa.py
kami_messenger/botconversa/test/__init__.py
kami_messenger/botconversa/test/test_botconversa.py
kami_messenger/contact/__init__.py
kami_messenger/contact/contact.py
kami_messenger/contact/test/__init__.py
kami_messenger/contact/test/test_contact.py
kami_messenger/email_messenger/__init__.py
kami_messenger/email_messenger/email_messenger.py
kami_messenger/email_messenger/test/__init__.py
kami_messenger/email_messenger/test/test_email.py
kami_messenger/kami_messenger.py
kami_messenger/messenger/__init__.py
kami_messenger/messenger/messenger.py
kami_messenger/messenger/test/__init__.py
kami_messenger/messenger/test/test_message.py
kami_messenger/static/img/icon.png
kami_messenger/templates/overdue_weekly.html
kami_messenger/templates/sales_montly.html
kami_messenger/templates/sales_weekly.html
kami_messenger/validator/__init__.py
kami_messenger/validator/custom_html_parser.py
kami_messenger/validator/test/__init__.py
kami_messenger/validator/test/test_custom_html_parser.py
kami_messenger/validator/test/test_validator.py
kami_messenger/validator/validator.py
kami_messenger/whatsapp/__init__.py
kami_messenger/whatsapp/tests/__init__.py
kami_messenger/whatsapp/tests/test_whatsapp.py
kami_messenger/whatsapp/whatsapp.py
kami_messenger-0.3.0.dist-info/LICENSE
kami_messenger-0.3.0.dist-info/METADATA
kami_messenger-0.3.0.dist-info/WHEEL
kami_messenger-0.3.0.dist-info/RECORD
