Metadata-Version: 2.1
Name: kami-messenger
Version: 0.3.0
Summary: Library to aggregate multiple messengers services
License: GNU 3.0
Author: Maicon de Menezes
Author-email: maicondmenezes@gmail.com
Requires-Python: >=3.9,<4.0
Classifier: Development Status :: 4 - Beta
Classifier: License :: Other/Proprietary License
Classifier: Natural Language :: English
Classifier: Programming Language :: Python :: 3
Classifier: Programming Language :: Python :: 3.9
Classifier: Programming Language :: Python :: 3.10
Classifier: Programming Language :: Python :: 3.11
Classifier: Topic :: Communications :: Email
Classifier: Topic :: Communications :: Telephony
Requires-Dist: jinja2 (>=3.1.2,<4.0.0)
Requires-Dist: kami-logging (>=0.2.0,<0.3.0)
Requires-Dist: phonenumbers (>=8.13.7,<9.0.0)
Requires-Dist: pydantic (>=1.10.6,<2.0.0)
Requires-Dist: python-dotenv (>=1.0.0,<2.0.0)
Requires-Dist: requests (>=2.28.2,<3.0.0)
Project-URL: Bug Tracker, https://github.com/devkami/kami-messenger/issues
Project-URL: Docs, https://kami-messenger.readthedocs.io/en/latest/
Project-URL: Source, https://github.com/devkami/kami-messenger
